LICENSE
README.md
wififtp.py
wififtp-0.1.1.dist-info/LICENSE
wififtp-0.1.1.dist-info/METADATA
wififtp-0.1.1.dist-info/WHEEL
wififtp-0.1.1.dist-info/entry_points.txt
wififtp-0.1.1.dist-info/RECORD
