Metadata-Version: 2.1
Name: wififtp
Version: 0.1.1
Summary: Share files between devices connected to same wlan/wifi/hotspot/router
Home-page: https://github.com/KasRoudra/WiFiFTP/
License: MIT
Author: KasRoudra
Author-email: kasroudrakrd@gmail.com
Requires-Python: >=3.9,<4.0
Classifier: License :: OSI Approved :: MIT License
Classifier: Programming Language :: Python :: 3
Classifier: Programming Language :: Python :: 3.9
Classifier: Programming Language :: Python :: 3.10
Classifier: Programming Language :: Python :: 3.11
Requires-Dist: pyftpdlib (>=1.5.0,<2.0.0)
Project-URL: Repository, https://github.com/KasRoudra/WiFiFTP/
